cci_facet_scanner/LICENSE
cci_facet_scanner/__init__.py
cci_facet_scanner/collection_handlers/__init__.py
cci_facet_scanner/collection_handlers/base.py
cci_facet_scanner/collection_handlers/cci.py
cci_facet_scanner/collection_handlers/cmip5.py
cci_facet_scanner/collection_handlers/utils/__init__.py
cci_facet_scanner/collection_handlers/utils/collection_map.py
cci_facet_scanner/collection_handlers/utils/facet_factory.py
cci_facet_scanner/collection_handlers/utils/moles_datasets.py
cci_facet_scanner/conf/cci_facet_scanner.ini
cci_facet_scanner/core/__init__.py
cci_facet_scanner/core/elasticsearch_connection.py
cci_facet_scanner/core/facet_scanner.py
cci_facet_scanner/scripts/__init__.py
cci_facet_scanner/scripts/facet_scanner_cmd.py
cci_facet_scanner/scripts/lotus_facet_scanner.py
cci_facet_scanner/scripts/lotus_worker.sh
cci_facet_scanner/scripts/test_cci_handler.py
cci_facet_scanner/tests/handlers/oldtest_cci.py
cci_facet_scanner/tests/test_consistency.py
cci_facet_scanner/tests/v2_endpoint.py
cci_facet_scanner/utils/__init__.py
cci_facet_scanner/utils/settings.py
cci_facet_scanner/utils/snippets.py
cci_facet_scanner-0.7.0.dist-info/METADATA
cci_facet_scanner-0.7.0.dist-info/WHEEL
cci_facet_scanner-0.7.0.dist-info/entry_points.txt
cci_facet_scanner-0.7.0.dist-info/RECORD
