Metadata-Version: 2.4
Name: cci-facet-scanner
Version: 0.7.0
Summary: Extracts facets from datasets to add to elasticsearch.
License: BSD 3
Author: Daniel Westwood
Author-email: daniel.westwood@stfc.ac.uk
Requires-Python: >=3.9,<4.0
Classifier: Intended Audience :: Developers
Classifier: License :: OSI Approved :: BSD License
Classifier: Operating System :: OS Independent
Classifier: Programming Language :: Python
Classifier: Programming Language :: Python :: 3
Requires-Dist: cci-tag-scanner (>=2.6.0)
Requires-Dist: elasticsearch (>=8,<9)
Requires-Dist: pytest (>=8.3.3,<9.0.0)
Requires-Dist: requests (>=2.32.3,<3.0.0)
Requires-Dist: sphinx (>=7,<8)
Requires-Dist: tqdm (>=4.66.6,<5.0.0)
